metamart_client/__init__.py
metamart_client/authentication.py
metamart_client/endpoints/__init__.py
metamart_client/endpoints/client.py
metamart_client/endpoints/rest.py
metamart_client/endpoints/utilities.py
metamart_client/endpoints/v1/__init__.py
metamart_client/endpoints/v1/client.py
metamart_client/endpoints/v1/delete.py
metamart_client/endpoints/v1/get/__init__.py
metamart_client/endpoints/v1/get/edge.py
metamart_client/endpoints/v1/get/node.py
metamart_client/endpoints/v1/get/organisation.py
metamart_client/endpoints/v1/get/source.py
metamart_client/endpoints/v1/get/utils.py
metamart_client/endpoints/v1/get/workspace.py
metamart_client/endpoints/v1/get.py
metamart_client/endpoints/v1/patch.py
metamart_client/endpoints/v1/post.py
metamart_client/endpoints/v1/url.py
metamart_client/endpoints/v1/utils.py
metamart_client/errors.py
metamart_client/integrations/__init__.py
metamart_client/integrations/base.py
metamart_client/py.typed
metamart_client/schemas/__init__.py
metamart_client/schemas/labels.py
metamart_client/schemas/schema.py
metamart_client/testing/__init__.py
metamart_client/testing/schema.py
metamart_client/update.py
metamart_client/utilities/__init__.py
metamart_client/utilities/tests.py
metamart_client-0.3.5.dist-info/METADATA
metamart_client-0.3.5.dist-info/WHEEL
metamart_client-0.3.5.dist-info/RECORD
