Metadata-Version: 2.1
Name: metamart-client
Version: 0.3.5
Summary: 
Home-page: https://www.metamart.io/
License: Elastic-2.0
Author: Ian Eaves
Author-email: ian@metamart.io
Requires-Python: >=3.8,<4.0
Classifier: License :: Other/Proprietary License
Classifier: Programming Language :: Python :: 3
Classifier: Programming Language :: Python :: 3.8
Classifier: Programming Language :: Python :: 3.9
Classifier: Programming Language :: Python :: 3.10
Classifier: Programming Language :: Python :: 3.11
Classifier: Programming Language :: Python :: 3.12
Requires-Dist: brotli (>=1.0.9,<2.0.0)
Requires-Dist: furl (>=2.1.3,<3.0.0)
Requires-Dist: httpx[http2] (>=0.24.0,<0.25.0)
Requires-Dist: metamart-schemas (>=0.2.4,<0.3.0)
Requires-Dist: more-itertools (>=9.1.0,<10.0.0)
Requires-Dist: multimethod (>=1.8,<2.0,!=1.11)
Requires-Dist: pydantic (>=1.9.1,<2.0.0)
Requires-Dist: pyyaml (>=6.0,<7.0)
Requires-Dist: requests (>=2.28.1,<3.0.0)
Requires-Dist: tqdm (>=4.65.0,<5.0.0)
Project-URL: Documentation, https://docs.metamart.io/
Project-URL: Repository, https://github.com/meta-mart/metamart-core/tree/master/metamart-client
